<BackupInst xmlns="http://www.microsoft.com/GroupPolicy/GPOOperations/Manifest"><GPOGuid><![CDATA[{df3179b2-552d-484a-a7df-a842d2df3639}]]></GPOGuid><GPODomain><![CDATA[ordix.local]]></GPODomain><GPODomainGuid><![CDATA[{4c727093-fa5a-4b56-b5b8-b946dff1a92b}]]></GPODomainGuid><GPODomainController><![CDATA[DC.ordix.local]]></GPODomainController><BackupTime><![CDATA[2022-04-05T16:03:31]]></BackupTime><ID><![CDATA[{C4C51F70-F903-427B-9A46-0D966559BC75}]]></ID><Comment><![CDATA[]]></Comment><GPODisplayName><![CDATA[GPO_COMP_PowerPlan]]></GPODisplayName></BackupInst>
